setup.py
pyTunes/__init__.py
pyTunes/pytunes.py
tunes.egg-info/PKG-INFO
tunes.egg-info/SOURCES.txt
tunes.egg-info/dependency_links.txt
tunes.egg-info/top_level.txt