Metadata-Version: 1.0
Name: tunes
Version: 1.0
Summary: A python scripting interface for iTunes
Home-page: https://github.com/robertf224/pyTunes/
Author: Robert Fidler
Author-email: robertf224@gmail.com
License: UNKNOWN
Keywords: iTunes,music,pyTunes,tunes,mac,osx
Platform: UNKNOWN
